PyHP3325A/HP3325A.py
PyHP3325A/__init__.py
PyHP3325A-0.3.dist-info/LICENSE
PyHP3325A-0.3.dist-info/METADATA
PyHP3325A-0.3.dist-info/WHEEL
PyHP3325A-0.3.dist-info/top_level.txt
PyHP3325A-0.3.dist-info/RECORD
