Metadata-Version: 2.1
Name: PyHP3325A
Version: 0.3
Summary: HP3478A python interface
Home-page: https://github.com/Minu-IU3IRR/PyHP3325A
Author: Manuel Minutello
License: MIT
License-File: LICENSE
Requires-Dist: PyAR488
